{
	"name": "Save_data_as_per_source_type",
	"properties": {
		"activities": [
			{
				"name": "copy data based of table",
				"type": "Copy",
				"dependsOn": [],
				"policy": {
					"timeout": "0.12:00:00",
					"retry": 0,
					"retryIntervalInSeconds": 30,
					"secureOutput": false,
					"secureInput": false
				},
				"userProperties": [],
				"typeProperties": {
					"source": {
						"type": "AzureSqlSource",
						"queryTimeout": "02:00:00",
						"partitionOption": "None"
					},
					"sink": {
						"type": "DelimitedTextSink",
						"storeSettings": {
							"type": "AzureBlobFSWriteSettings"
						},
						"formatSettings": {
							"type": "DelimitedTextWriteSettings",
							"quoteAllText": true,
							"fileExtension": ".txt"
						}
					},
					"enableStaging": false,
					"translator": {
						"type": "TabularTranslator",
						"typeConversion": true,
						"typeConversionSettings": {
							"allowDataTruncation": true,
							"treatBooleanAsNumber": false
						}
					}
				},
				"inputs": [
					{
						"referenceName": "Gen_SQL_DS",
						"type": "DatasetReference",
						"parameters": {
							"SchemaName": "saleslt",
							"tableName": "CustomerAddress"
						}
					}
				],
				"outputs": [
					{
						"referenceName": "Gen_Adls_Csv_DS",
						"type": "DatasetReference",
						"parameters": {
							"FilePath": "CustomerAddress"
						}
					}
				]
			}
		],
		"annotations": [],
		"lastPublishTime": "2026-04-20T18:26:10Z"
	},
	"type": "Microsoft.DataFactory/factories/pipelines"
}